Metadata-Version: 2.1
Name: Dts-OpenFisca-Core
Version: 34.8.0
Summary: A versatile microsimulation free software
Home-page: https://github.com/openfisca/openfisca-core
Author: OpenFisca Team
Author-email: contact@openfisca.org
License: https://www.fsf.org/licensing/licenses/agpl-3.0.html
Keywords: benefit microsimulation social tax
Platform: UNKNOWN
Classifier: Development Status :: 5 - Production/Stable
Classifier: License :: OSI Approved :: GNU Affero General Public License v3
Classifier: Operating System :: POSIX
Classifier: Programming Language :: Python
Classifier: Programming Language :: Python :: 3.6
Classifier: Programming Language :: Python :: 3.7
Classifier: Topic :: Scientific/Engineering :: Information Analysis
Requires-Dist: dpath (<2.0.0,>=1.5.0)
Requires-Dist: pytest (<6.0.0,>=4.4.1)
Requires-Dist: numpy (<1.18,>=1.11)
Requires-Dist: psutil (<6.0.0,>=5.4.7)
Requires-Dist: PyYAML (>=3.10)
Requires-Dist: sortedcontainers (==2.2.2)
Requires-Dist: numexpr (<=3.0,>=2.7.0)
Provides-Extra: dev
Requires-Dist: autopep8 (<1.6.0,>=1.4.0) ; extra == 'dev'
Requires-Dist: flake8 (<3.9.0,>=3.7.0) ; extra == 'dev'
Requires-Dist: flake8-bugbear (<20.0.0,>=19.3.0) ; extra == 'dev'
Requires-Dist: flake8-print (<4.0.0,>=3.1.0) ; extra == 'dev'
Requires-Dist: pytest-cov (<3.0.0,>=2.6.1) ; extra == 'dev'
Requires-Dist: mypy (<0.800,>=0.701) ; extra == 'dev'
Requires-Dist: openfisca-country-template (<4.0.0,>=3.10.0) ; extra == 'dev'
Requires-Dist: openfisca-extension-template (<2.0.0,>=1.2.0rc0) ; extra == 'dev'
Requires-Dist: werkzeug (<2.0.0,>=1.0.0) ; extra == 'dev'
Requires-Dist: flask (==1.1.2) ; extra == 'dev'
Requires-Dist: flask-cors (==3.0.7) ; extra == 'dev'
Requires-Dist: gunicorn (<21.0.0,>=20.0.0) ; extra == 'dev'
Provides-Extra: tracker
Requires-Dist: openfisca-tracker (==0.4.0) ; extra == 'tracker'
Provides-Extra: web-api
Requires-Dist: werkzeug (<2.0.0,>=1.0.0) ; extra == 'web-api'
Requires-Dist: flask (==1.1.2) ; extra == 'web-api'
Requires-Dist: flask-cors (==3.0.7) ; extra == 'web-api'
Requires-Dist: gunicorn (<21.0.0,>=20.0.0) ; extra == 'web-api'
